jaxga/__init__.py
jaxga/jaxga.py
jaxga/mv.py
jaxga/signatures.py
jaxga/flaxmodules/__init__.py
jaxga/flaxmodules/mvproddense.py
jaxga/ops/__init__.py
jaxga/ops/add.py
jaxga/ops/dual.py
jaxga/ops/inverse.py
jaxga/ops/keepnonzero.py
jaxga/ops/multiply.py
jaxga/ops/reduce_same.py
jaxga/ops/select.py
jaxga/ops/simple_exp.py
jaxga-0.0.2.dist-info/LICENSE
jaxga-0.0.2.dist-info/METADATA
jaxga-0.0.2.dist-info/WHEEL
jaxga-0.0.2.dist-info/top_level.txt
jaxga-0.0.2.dist-info/RECORD
